{
    "event_id": "evt_001",
    "video_id": "755dfad5-6d32-43e5-89e6-a9a43c0b6a34",
    "start_time": 0.0,
    "end_time": 1.0,
    "timestamp_start_seconds": 0.0,
    "timestamp_end_seconds": 1.0,
    "timestamp_start_human": "00:00:00",
    "timestamp_end_human": "00:00:01",
    "duration_seconds": 1.0,
    "frame_count": 1,
    "objects": [
        {
            "type": "roadway",
            "subtype": "paved street",
            "color": "gray",
            "attributes": []
        },
        {
            "type": "shadow",
            "subtype": "tree shadow",
            "color": "black",
            "attributes": [
                "long",
                "slanted across pavement"
            ]
        }
    ],
    "activities": [],
    "primary_object": "Subject",
    "color": "",
    "primary_activity": "present",
    "source_frames": [
        "755dfad5-6d32-43e5-89e6-a9a43c0b6a34_f0001"
    ],
    "event_type": "motion_detected",
    "summary": "Subject was present at the monitored area.",
    "scene_context": "a paved road surface under daylight conditions, showing shadows from trees cast on it.",
    "real_world_time": null,
    "actor_description": "",
    "participants": [],
    "participant_count": 0,
    "behavioral_flags": [],
    "confidence": 0.485,
    "narrative_sentence": "Subject was present at the monitored area.",
    "location_text": "the monitored area",
    "event_severity": 15,
    "unified_text": "a quiet daytime scene featuring long tree shadows stretching across a smooth asphalt roadway. a paved road surface under daylight conditions, showing shadows from trees cast on it. street view daylight shadows trees roadway paved street shadow tree shadow long slanted across pavement"
}